mordu/__init__.py
mordu/alpha_0.py
mordu/alpha_r_cubic.py
mordu/alpha_r_helmholtz.py
mordu/alpha_r_saft.py
mordu/cp0.py
mordu/eos.py
mordu/purefluid.py
mordu/symbols.py
mordu/utilities.py
mordu/storeroom/__init__.py
mordu/storeroom/alpha_r_func.py
mordu/storeroom/cp0s.py
mordu/storeroom/eos_purefluid.py
mordu/storeroom/fluids.py
mordu-0.0.26.dist-info/METADATA
mordu-0.0.26.dist-info/WHEEL
mordu-0.0.26.dist-info/licenses/LICENSE
mordu-0.0.26.dist-info/RECORD
