Metadata-Version: 2.4
Name: mordu
Version: 0.0.26
Summary: A python package for the development and assessment of user defined equations of state.
Project-URL: Homepage, https://github.com/CatDN/eos
Project-URL: Issues, https://github.com/CatDN/eos/issues
Author-email: Cat <catarina.duarte-nunes18@ic.ac.uk>
License-Expression: MIT
License-File: LICENSE
Classifier: Operating System :: OS Independent
Classifier: Programming Language :: Python :: 3
Requires-Python: >=3.11
Requires-Dist: numpy>=2.3.1
Requires-Dist: pandas>=2.3.0
Requires-Dist: scipy>=1.16.0
Requires-Dist: sympy>=1.14.0
